paper_qa_pypdf-2026.1.5.dist-info/licenses/LICENSE
paperqa_pypdf/__init__.py
paperqa_pypdf/py.typed
paperqa_pypdf/reader.py
paperqa_pypdf/utils.py
paperqa_pypdf/version.py
paper_qa_pypdf-2026.1.5.dist-info/METADATA
paper_qa_pypdf-2026.1.5.dist-info/WHEEL
paper_qa_pypdf-2026.1.5.dist-info/top_level.txt
paper_qa_pypdf-2026.1.5.dist-info/RECORD
