Metadata-Version: 2.4
Name: paper-qa-pypdf
Version: 2026.1.5
Summary: PaperQA readers implemented using PyPDF
Author-email: FutureHouse technical staff <hello@futurehouse.org>
Maintainer-email: James Braza <jamesbraza@gmail.com>, Michael Skarlinski <michael.skarlinski@gmail.com>, Andrew White <white.d.andrew@gmail.com>
License:                                  Apache License
Classifier: Intended Audience :: Developers
Classifier: License :: OSI Approved :: Apache Software License
Classifier: Operating System :: OS Independent
Classifier: Programming Language :: Python :: 3 :: Only
Classifier: Programming Language :: Python :: 3.11
Classifier: Programming Language :: Python :: 3.12
Classifier: Programming Language :: Python :: 3.13
Classifier: Programming Language :: Python
Classifier: Topic :: Scientific/Engineering :: Artificial Intelligence
Requires-Python: >=3.11
License-File: LICENSE
Requires-Dist: PyPDF>=3
Requires-Dist: paper-qa
Provides-Extra: dev
Requires-Dist: fhlmi>=0.39; extra == "dev"
Requires-Dist: paper-qa-pypdf[enhanced,media]; extra == "dev"
Requires-Dist: paper-qa>=5.23; extra == "dev"
Requires-Dist: pytest-asyncio; extra == "dev"
Requires-Dist: pytest-rerunfailures; extra == "dev"
Requires-Dist: pytest>=8; extra == "dev"
Provides-Extra: enhanced
Requires-Dist: paper-qa-pypdf[media]; extra == "enhanced"
Requires-Dist: pdfplumber>=0.5; extra == "enhanced"
Provides-Extra: media
Requires-Dist: Pillow; extra == "media"
Requires-Dist: PyPDF[image]; extra == "media"
Requires-Dist: pypdfium2>=4.22.0; extra == "media"
Dynamic: license-file
